tinkoff_invest/__init__.py
tinkoff_invest/base_session.py
tinkoff_invest/base_strategy.py
tinkoff_invest/config.py
tinkoff_invest/exceptions.py
tinkoff_invest/session.py
tinkoff_invest/subscriptions.py
tinkoff_invest/models/__init__.py
tinkoff_invest/models/account.py
tinkoff_invest/models/candle.py
tinkoff_invest/models/instrument.py
tinkoff_invest/models/instrument_status.py
tinkoff_invest/models/money.py
tinkoff_invest/models/operation.py
tinkoff_invest/models/order.py
tinkoff_invest/models/order_book.py
tinkoff_invest/models/portfolio.py
tinkoff_invest/models/types.py
tinkoff_invest-1.0.5.dist-info/LICENSE
tinkoff_invest-1.0.5.dist-info/METADATA
tinkoff_invest-1.0.5.dist-info/WHEEL
tinkoff_invest-1.0.5.dist-info/top_level.txt
tinkoff_invest-1.0.5.dist-info/RECORD
